{"name":"Buy of Bag the Module \"Mi carrito\"","id":"bag-buy;buy-of-bag-the-module-\"mi-carrito\"","testSteps":[{"number":1,"description":"Given he user enter the website","duration":12513,"startTime":"2023-09-14T16:31:45.326-05:00[America/Bogota]","screenshots":[{"screenshot":"2f30eb12c8da3026fbae870106c33b21e76a93f382e9b56ea195702128d8306d.png","timeStamp":1694727117839}],"result":"SUCCESS","precondition":false,"level":0,"children":[{"number":2,"description":"Rosa opens the https://www.bon-bonite.com/","duration":12256,"startTime":"2023-09-14T16:31:45.561-05:00[America/Bogota]","screenshots":[{"screenshot":"2f30eb12c8da3026fbae870106c33b21e76a93f382e9b56ea195702128d8306d.png","timeStamp":1694727117816}],"result":"SUCCESS","precondition":false,"level":1}]},{"number":3,"description":"When The user select a product in the Wallets module carrito and complete the forms for facturation\r\n| name | surname | n_documento | email | phone | adrres | code_zip |\r\n| Cristian Camilo | Ruano | 123456789 | camilo90@gmail.com | 09787654321 | Cra 3#42 | fr4frw3444555 |","duration":57046,"startTime":"2023-09-14T16:31:57.842-05:00[America/Bogota]","screenshots":[{"screenshot":"2f30eb12c8da3026fbae870106c33b21e76a93f382e9b56ea195702128d8306d.png","timeStamp":1694727117857}],"exception":{"errorType":"org.openqa.selenium.ElementClickInterceptedException","message":"element click intercepted: Element \u003cinput id\u003d\"ship-to-different-address-checkbox\" class\u003d\"woocommerce-form__input woocommerce-form__input-checkbox input-checkbox\" type\u003d\"checkbox\" name\u003d\"ship_to_different_address\" value\u003d\"1\"\u003e is not clickable at point (497, 912). Other element would receive the click: \u003cdiv class\u003d\"message_bar\"\u003e...\u003c/div\u003e\n  (Session info: chrome\u003d116.0.5845.188)\nBuild info: version: \u00273.141.59\u0027, revision: \u0027e82be7d358\u0027, time: \u00272018-11-14T08:17:03\u0027\nSystem info: host: \u0027DESKTOP-SN1JVCC\u0027, ip: \u0027192.168.56.1\u0027, os.name: \u0027Windows 10\u0027, os.arch: \u0027amd64\u0027, os.version: \u002710.0\u0027, java.version: \u00271.8.0_161\u0027\nDriver info: org.openqa.selenium.chrome.ChromeDriver\nCapabilities {acceptInsecureCerts: false, browserName: chrome, browserVersion: 116.0.5845.188, chrome: {chromedriverVersion: 116.0.5845.96 (1a3918166880..., userDataDir: C:\\Users\\FABRIC~1\\AppData\\L...}, fedcm:accounts: true, goog:chromeOptions: {debuggerAddress: localhost:59975}, javascriptEnabled: true, networkConnectionEnabled: false, pageLoadStrategy: normal, platform: WINDOWS, platformName: WINDOWS, proxy: Proxy(), setWindowRect: true, strictFileInteractability: false, timeouts: {implicit: 0, pageLoad: 300000, script: 30000}, unhandledPromptBehavior: dismiss and notify, webauthn:extension:credBlob: true, webauthn:extension:largeBlob: true, webauthn:extension:minPinLength: true, webauthn:extension:prf: true, webauthn:virtualAuthenticators: true}\nSession ID: 4903b9d8a307dc9daa7a46383c3f82c2","stackTrace":[{"declaringClass":"com.co.bonbonite.tasks.FacturationBag","methodName":"performAs","fileName":"FacturationBag.java","lineNumber":94},{"declaringClass":"com.co.bonbonite.stepsdefinitions.BagStepsDefinitions","methodName":"theUserSelectAProductInTheWalletsModuleCarritoAndCompleteTheFormsForFacturation","fileName":"BagStepsDefinitions.java","lineNumber":58},{"declaringClass":"cucumber.runner.Runner","methodName":"runPickle","fileName":"Runner.java","lineNumber":80},{"declaringClass":"worker.org.gradle.process.internal.worker.GradleWorkerMain","methodName":"run","fileName":"GradleWorkerMain.java","lineNumber":69},{"declaringClass":"worker.org.gradle.process.internal.worker.GradleWorkerMain","methodName":"main","fileName":"GradleWorkerMain.java","lineNumber":74}]},"result":"ERROR","precondition":false,"level":0,"children":[{"number":4,"description":"Rosa bags buy","duration":24939,"startTime":"2023-09-14T16:31:57.874-05:00[America/Bogota]","screenshots":[{"screenshot":"c8ab47df3e1e8f39c53cd0d8b6d796daea2088c25938322d7dc0d52360e283eb.png","timeStamp":1694727119324},{"screenshot":"22f8092ff714a01faaefa1773cdd199b476ea0b721d561694db1d02232357002.png","timeStamp":1694727142813}],"result":"SUCCESS","precondition":false,"level":1,"children":[{"number":5,"description":"Rosa clicks on ir al modulo de bolsos","duration":8767,"startTime":"2023-09-14T16:31:59.333-05:00[America/Bogota]","screenshots":[{"screenshot":"c8ab47df3e1e8f39c53cd0d8b6d796daea2088c25938322d7dc0d52360e283eb.png","timeStamp":1694727119340},{"screenshot":"226da2645102fbf922012a8f3a440901e3242ce88900debdc13e14b6fbf640f1.png","timeStamp":1694727128100}],"result":"SUCCESS","precondition":false,"level":2},{"number":6,"description":"Rosa clicks on ir al tipos de bolsos","duration":4238,"startTime":"2023-09-14T16:32:08.106-05:00[America/Bogota]","screenshots":[{"screenshot":"226da2645102fbf922012a8f3a440901e3242ce88900debdc13e14b6fbf640f1.png","timeStamp":1694727128118},{"screenshot":"287a67954d6e571893f924086855acb4afb3a91b6ae69ca43a12ab96160a047b.png","timeStamp":1694727132343}],"result":"SUCCESS","precondition":false,"level":2},{"number":7,"description":"Rosa clicks on seleccionar bolsos","duration":2855,"startTime":"2023-09-14T16:32:12.347-05:00[America/Bogota]","screenshots":[{"screenshot":"287a67954d6e571893f924086855acb4afb3a91b6ae69ca43a12ab96160a047b.png","timeStamp":1694727132356},{"screenshot":"9d6959180b2d726ad754ca7bbe8f506292c99cafb3ac384e2c242e5ffc168492.png","timeStamp":1694727135202}],"result":"SUCCESS","precondition":false,"level":2},{"number":8,"description":"Rosa clicks on comprar bolsos","duration":4403,"startTime":"2023-09-14T16:32:15.208-05:00[America/Bogota]","screenshots":[{"screenshot":"9d6959180b2d726ad754ca7bbe8f506292c99cafb3ac384e2c242e5ffc168492.png","timeStamp":1694727135215},{"screenshot":"3976fa5f0761e550ee3189ea4f07429a28138d5e67bdf5b65bdc3a1d99496492.png","timeStamp":1694727139611}],"result":"SUCCESS","precondition":false,"level":2}]},{"number":9,"description":"Rosa facturation bag","duration":32057,"startTime":"2023-09-14T16:32:22.824-05:00[America/Bogota]","screenshots":[{"screenshot":"22f8092ff714a01faaefa1773cdd199b476ea0b721d561694db1d02232357002.png","timeStamp":1694727142839}],"exception":{"errorType":"org.openqa.selenium.ElementClickInterceptedException","message":"element click intercepted: Element \u003cinput id\u003d\"ship-to-different-address-checkbox\" class\u003d\"woocommerce-form__input woocommerce-form__input-checkbox input-checkbox\" type\u003d\"checkbox\" name\u003d\"ship_to_different_address\" value\u003d\"1\"\u003e is not clickable at point (497, 912). Other element would receive the click: \u003cdiv class\u003d\"message_bar\"\u003e...\u003c/div\u003e\n  (Session info: chrome\u003d116.0.5845.188)\nBuild info: version: \u00273.141.59\u0027, revision: \u0027e82be7d358\u0027, time: \u00272018-11-14T08:17:03\u0027\nSystem info: host: \u0027DESKTOP-SN1JVCC\u0027, ip: \u0027192.168.56.1\u0027, os.name: \u0027Windows 10\u0027, os.arch: \u0027amd64\u0027, os.version: \u002710.0\u0027, java.version: \u00271.8.0_161\u0027\nDriver info: org.openqa.selenium.chrome.ChromeDriver\nCapabilities {acceptInsecureCerts: false, browserName: chrome, browserVersion: 116.0.5845.188, chrome: {chromedriverVersion: 116.0.5845.96 (1a3918166880..., userDataDir: C:\\Users\\FABRIC~1\\AppData\\L...}, fedcm:accounts: true, goog:chromeOptions: {debuggerAddress: localhost:59975}, javascriptEnabled: true, networkConnectionEnabled: false, pageLoadStrategy: normal, platform: WINDOWS, platformName: WINDOWS, proxy: Proxy(), setWindowRect: true, strictFileInteractability: false, timeouts: {implicit: 0, pageLoad: 300000, script: 30000}, unhandledPromptBehavior: dismiss and notify, webauthn:extension:credBlob: true, webauthn:extension:largeBlob: true, webauthn:extension:minPinLength: true, webauthn:extension:prf: true, webauthn:virtualAuthenticators: true}\nSession ID: 4903b9d8a307dc9daa7a46383c3f82c2","stackTrace":[{"declaringClass":"com.co.bonbonite.tasks.FacturationBag","methodName":"performAs","fileName":"FacturationBag.java","lineNumber":94},{"declaringClass":"com.co.bonbonite.stepsdefinitions.BagStepsDefinitions","methodName":"theUserSelectAProductInTheWalletsModuleCarritoAndCompleteTheFormsForFacturation","fileName":"BagStepsDefinitions.java","lineNumber":58},{"declaringClass":"cucumber.runner.Runner","methodName":"runPickle","fileName":"Runner.java","lineNumber":80},{"declaringClass":"worker.org.gradle.process.internal.worker.GradleWorkerMain","methodName":"run","fileName":"GradleWorkerMain.java","lineNumber":69},{"declaringClass":"worker.org.gradle.process.internal.worker.GradleWorkerMain","methodName":"main","fileName":"GradleWorkerMain.java","lineNumber":74}]},"result":"ERROR","precondition":false,"level":1,"children":[{"number":10,"description":"Rosa clicks on finalizar compra","duration":4637,"startTime":"2023-09-14T16:32:22.847-05:00[America/Bogota]","screenshots":[{"screenshot":"22f8092ff714a01faaefa1773cdd199b476ea0b721d561694db1d02232357002.png","timeStamp":1694727142854},{"screenshot":"12cdd6475cb32c4b1719df48957452a61369eba12f10045cd09fb9d0af66ba6f.png","timeStamp":1694727147484}],"result":"SUCCESS","precondition":false,"level":2},{"number":11,"description":"Rosa clicks on continuar compra","duration":583,"startTime":"2023-09-14T16:32:29.502-05:00[America/Bogota]","screenshots":[{"screenshot":"f2cfc244923856c25bf340e7340a8683255b601adb96846e0ba9a9bdf5f6d15c.png","timeStamp":1694727149707},{"screenshot":"a2caf9a1e5c01418d01d8a0d7614533cba4c81d0a7ccfabeecb0763a2e40c41a.png","timeStamp":1694727150085}],"result":"SUCCESS","precondition":false,"level":2},{"number":12,"description":"Rosa clicks on escribir nombre","duration":556,"startTime":"2023-09-14T16:32:32.100-05:00[America/Bogota]","screenshots":[{"screenshot":"47e71773d46d999260466fd7290b422559354ce4a9d41cc03396e107c8225dd8.png","timeStamp":1694727152277},{"screenshot":"2c7492c6dd4cf08a825443c15cb0e1ea45e55b704510ba6df8e13474ad19995c.png","timeStamp":1694727152656}],"result":"SUCCESS","precondition":false,"level":2},{"number":13,"description":"Rosa enters \u0027Cristian Camilo\u0027 into escribir nombre","duration":567,"startTime":"2023-09-14T16:32:32.663-05:00[America/Bogota]","screenshots":[{"screenshot":"2c7492c6dd4cf08a825443c15cb0e1ea45e55b704510ba6df8e13474ad19995c.png","timeStamp":1694727152669},{"screenshot":"fd3a9fa97f2fcc98b389f4fbf12d9aab6b965f47b79b1bbe0dbc596f8f0c9651.png","timeStamp":1694727153230}],"result":"SUCCESS","precondition":false,"level":2},{"number":14,"description":"Rosa enters \u0027Ruano\u0027 into escribir apellidos","duration":458,"startTime":"2023-09-14T16:32:33.233-05:00[America/Bogota]","screenshots":[{"screenshot":"fd3a9fa97f2fcc98b389f4fbf12d9aab6b965f47b79b1bbe0dbc596f8f0c9651.png","timeStamp":1694727153239},{"screenshot":"2ae23c4e42bb35b420e1c736ba6b9692a82b86a54f8374fa5ea21c19c00717d7.png","timeStamp":1694727153691}],"result":"SUCCESS","precondition":false,"level":2},{"number":15,"description":"Rosa clicks on escribir apellidos","duration":393,"startTime":"2023-09-14T16:32:33.694-05:00[America/Bogota]","screenshots":[{"screenshot":"2ae23c4e42bb35b420e1c736ba6b9692a82b86a54f8374fa5ea21c19c00717d7.png","timeStamp":1694727153700},{"screenshot":"660c979d2e72e86a2d99046c0df018ee0b0f11ce312df7b86dbefe40d7c00b00.png","timeStamp":1694727154087}],"result":"SUCCESS","precondition":false,"level":2},{"number":16,"description":"Rosa clicks on seleccionar sexo","duration":614,"startTime":"2023-09-14T16:32:36.103-05:00[America/Bogota]","screenshots":[{"screenshot":"660c979d2e72e86a2d99046c0df018ee0b0f11ce312df7b86dbefe40d7c00b00.png","timeStamp":1694727156326},{"screenshot":"660c979d2e72e86a2d99046c0df018ee0b0f11ce312df7b86dbefe40d7c00b00.png","timeStamp":1694727156717}],"result":"SUCCESS","precondition":false,"level":2},{"number":17,"description":"Rosa clicks on seleccionar sexo","duration":468,"startTime":"2023-09-14T16:32:36.720-05:00[America/Bogota]","screenshots":[{"screenshot":"660c979d2e72e86a2d99046c0df018ee0b0f11ce312df7b86dbefe40d7c00b00.png","timeStamp":1694727156729},{"screenshot":"9c674e0b6305b040fd8cdac2ac9bd4a9d669f6ad4a2a6ec9d705ea3847562345.png","timeStamp":1694727157188}],"result":"SUCCESS","precondition":false,"level":2},{"number":18,"description":"Rosa clicks on seleccionar sexo","duration":582,"startTime":"2023-09-14T16:32:40.196-05:00[America/Bogota]","screenshots":[{"screenshot":"9c674e0b6305b040fd8cdac2ac9bd4a9d669f6ad4a2a6ec9d705ea3847562345.png","timeStamp":1694727160387},{"screenshot":"9c674e0b6305b040fd8cdac2ac9bd4a9d669f6ad4a2a6ec9d705ea3847562345.png","timeStamp":1694727160778}],"result":"SUCCESS","precondition":false,"level":2},{"number":19,"description":"Rosa enters \u0027123456789\u0027 into seleccionar sexo","duration":532,"startTime":"2023-09-14T16:32:40.781-05:00[America/Bogota]","screenshots":[{"screenshot":"9c674e0b6305b040fd8cdac2ac9bd4a9d669f6ad4a2a6ec9d705ea3847562345.png","timeStamp":1694727160787},{"screenshot":"7840f396693246ec5d17f027b880b0cd3ada54ac080dca8d001e3c747e4a03f2.png","timeStamp":1694727161313}],"result":"SUCCESS","precondition":false,"level":2},{"number":20,"description":"Rosa enters \u0027camilo90@gmail.com\u0027 into seleccionar sexo","duration":717,"startTime":"2023-09-14T16:32:41.429-05:00[America/Bogota]","screenshots":[{"screenshot":"68c58ca88d7fd71ccbea682040aa79af6aa22fe777e867c49c127d58a4a3d592.png","timeStamp":1694727161640},{"screenshot":"da49d7030d2aac84cd9643557ff53014cc0d21f638ccb5675587aceb6c164c4f.png","timeStamp":1694727162146}],"result":"SUCCESS","precondition":false,"level":2},{"number":21,"description":"Rosa enters \u002709787654321\u0027 into seleccionar sexo","duration":476,"startTime":"2023-09-14T16:32:42.149-05:00[America/Bogota]","screenshots":[{"screenshot":"da49d7030d2aac84cd9643557ff53014cc0d21f638ccb5675587aceb6c164c4f.png","timeStamp":1694727162159},{"screenshot":"cc1c825f1084a3187175b87154c5106caf377e20081f86287946da99273e07e1.png","timeStamp":1694727162625}],"result":"SUCCESS","precondition":false,"level":2},{"number":22,"description":"Rosa clicks on seleccionar pais","duration":557,"startTime":"2023-09-14T16:32:42.628-05:00[America/Bogota]","screenshots":[{"screenshot":"cc1c825f1084a3187175b87154c5106caf377e20081f86287946da99273e07e1.png","timeStamp":1694727162634},{"screenshot":"91210fa26505194c07c320bc33ee4d39aa5e50c5e6a6075c9010ba7b7131b787.png","timeStamp":1694727163185}],"result":"SUCCESS","precondition":false,"level":2},{"number":23,"description":"Rosa clicks on op pais","duration":519,"startTime":"2023-09-14T16:32:45.190-05:00[America/Bogota]","screenshots":[{"screenshot":"91210fa26505194c07c320bc33ee4d39aa5e50c5e6a6075c9010ba7b7131b787.png","timeStamp":1694727165368},{"screenshot":"91210fa26505194c07c320bc33ee4d39aa5e50c5e6a6075c9010ba7b7131b787.png","timeStamp":1694727165709}],"result":"SUCCESS","precondition":false,"level":2},{"number":24,"description":"Rosa clicks on seleccionar departamento","duration":386,"startTime":"2023-09-14T16:32:45.715-05:00[America/Bogota]","screenshots":[{"screenshot":"91210fa26505194c07c320bc33ee4d39aa5e50c5e6a6075c9010ba7b7131b787.png","timeStamp":1694727165722},{"screenshot":"5b74ce48c560ff34bb6aa9e37a8e1eaa22aa09323dcf88770bbf42f8fe6c77d0.png","timeStamp":1694727166101}],"result":"SUCCESS","precondition":false,"level":2},{"number":25,"description":"Rosa clicks on op departamento","duration":598,"startTime":"2023-09-14T16:32:47.214-05:00[America/Bogota]","screenshots":[{"screenshot":"77f2325c095d55ffa624e08d2a69a4a0a856883e480a9843a27f6c5c202c5112.png","timeStamp":1694727167406},{"screenshot":"65c1c62e5afa8f9221be64a6fb7c3f2d5c72cf3768c72fb6313c0aaa0b6da21d.png","timeStamp":1694727167812}],"result":"SUCCESS","precondition":false,"level":2},{"number":26,"description":"Rosa clicks on seleccionar city","duration":395,"startTime":"2023-09-14T16:32:47.814-05:00[America/Bogota]","screenshots":[{"screenshot":"65c1c62e5afa8f9221be64a6fb7c3f2d5c72cf3768c72fb6313c0aaa0b6da21d.png","timeStamp":1694727167823},{"screenshot":"5a21bc623192a24f1a34e8796df59b3a216c42a5092e240bc46d39a201942d8a.png","timeStamp":1694727168209}],"result":"SUCCESS","precondition":false,"level":2},{"number":27,"description":"Rosa clicks on op city","duration":507,"startTime":"2023-09-14T16:32:49.216-05:00[America/Bogota]","screenshots":[{"screenshot":"5a21bc623192a24f1a34e8796df59b3a216c42a5092e240bc46d39a201942d8a.png","timeStamp":1694727169382},{"screenshot":"b0f5ae89d2906e5ba16a28e2bf37d9cfb730a0ab409d0cb2a5de40a2b1700a80.png","timeStamp":1694727169723}],"result":"SUCCESS","precondition":false,"level":2},{"number":28,"description":"Rosa enters \u0027Cra 3#42\u0027 into escribir direccion","duration":513,"startTime":"2023-09-14T16:32:49.728-05:00[America/Bogota]","screenshots":[{"screenshot":"b0f5ae89d2906e5ba16a28e2bf37d9cfb730a0ab409d0cb2a5de40a2b1700a80.png","timeStamp":1694727169739},{"screenshot":"5fcfe85de0f0364d04d2ca22a507e058b693a72b37bdb20df8f77359bfe5d3cf.png","timeStamp":1694727170241}],"result":"SUCCESS","precondition":false,"level":2},{"number":29,"description":"Rosa enters \u0027fr4frw3444555\u0027 into escribir direccion","duration":503,"startTime":"2023-09-14T16:32:50.243-05:00[America/Bogota]","screenshots":[{"screenshot":"5fcfe85de0f0364d04d2ca22a507e058b693a72b37bdb20df8f77359bfe5d3cf.png","timeStamp":1694727170249},{"screenshot":"9aaf8c1b1cb2e91f01f486545c384ef8ee2119fc3d3a36835fc12744b092c45c.png","timeStamp":1694727170746}],"result":"SUCCESS","precondition":false,"level":2},{"number":30,"description":"Rosa clicks on autorizar 1","duration":2035,"startTime":"2023-09-14T16:32:52.840-05:00[America/Bogota]","screenshots":[{"screenshot":"9aaf8c1b1cb2e91f01f486545c384ef8ee2119fc3d3a36835fc12744b092c45c.png","timeStamp":1694727173000},{"screenshot":"627665eeea11aa5bc666d4a21fbac173d41265963c6c8b40639bda653bf44a80.png","htmlSource":"pagesource4955011295067766555.html.txt","timeStamp":1694727174870}],"exception":{"errorType":"org.openqa.selenium.ElementClickInterceptedException","message":"element click intercepted: Element \u003cinput id\u003d\"ship-to-different-address-checkbox\" class\u003d\"woocommerce-form__input woocommerce-form__input-checkbox input-checkbox\" type\u003d\"checkbox\" name\u003d\"ship_to_different_address\" value\u003d\"1\"\u003e is not clickable at point (497, 912). Other element would receive the click: \u003cdiv class\u003d\"message_bar\"\u003e...\u003c/div\u003e\n  (Session info: chrome\u003d116.0.5845.188)\nBuild info: version: \u00273.141.59\u0027, revision: \u0027e82be7d358\u0027, time: \u00272018-11-14T08:17:03\u0027\nSystem info: host: \u0027DESKTOP-SN1JVCC\u0027, ip: \u0027192.168.56.1\u0027, os.name: \u0027Windows 10\u0027, os.arch: \u0027amd64\u0027, os.version: \u002710.0\u0027, java.version: \u00271.8.0_161\u0027\nDriver info: org.openqa.selenium.chrome.ChromeDriver\nCapabilities {acceptInsecureCerts: false, browserName: chrome, browserVersion: 116.0.5845.188, chrome: {chromedriverVersion: 116.0.5845.96 (1a3918166880..., userDataDir: C:\\Users\\FABRIC~1\\AppData\\L...}, fedcm:accounts: true, goog:chromeOptions: {debuggerAddress: localhost:59975}, javascriptEnabled: true, networkConnectionEnabled: false, pageLoadStrategy: normal, platform: WINDOWS, platformName: WINDOWS, proxy: Proxy(), setWindowRect: true, strictFileInteractability: false, timeouts: {implicit: 0, pageLoad: 300000, script: 30000}, unhandledPromptBehavior: dismiss and notify, webauthn:extension:credBlob: true, webauthn:extension:largeBlob: true, webauthn:extension:minPinLength: true, webauthn:extension:prf: true, webauthn:virtualAuthenticators: true}\nSession ID: 4903b9d8a307dc9daa7a46383c3f82c2","stackTrace":[{"declaringClass":"com.co.bonbonite.tasks.FacturationBag","methodName":"performAs","fileName":"FacturationBag.java","lineNumber":94},{"declaringClass":"com.co.bonbonite.stepsdefinitions.BagStepsDefinitions","methodName":"theUserSelectAProductInTheWalletsModuleCarritoAndCompleteTheFormsForFacturation","fileName":"BagStepsDefinitions.java","lineNumber":58},{"declaringClass":"cucumber.runner.Runner","methodName":"runPickle","fileName":"Runner.java","lineNumber":80},{"declaringClass":"worker.org.gradle.process.internal.worker.GradleWorkerMain","methodName":"run","fileName":"GradleWorkerMain.java","lineNumber":69},{"declaringClass":"worker.org.gradle.process.internal.worker.GradleWorkerMain","methodName":"main","fileName":"GradleWorkerMain.java","lineNumber":74}]},"result":"ERROR","precondition":false,"level":2}]}]},{"number":31,"description":"Then the user would have bought a bag","duration":7,"startTime":"2023-09-14T16:32:54.901-05:00[America/Bogota]","result":"SKIPPED","precondition":false,"level":0}],"userStory":{"id":"bag-buy","storyName":"Bag buy","path":"src/test/resources/features/bag.feature","narrative":"  i need buy a bag","type":"feature"},"featureTag":{"name":"Features/Bag buy","type":"feature","displayName":"Features/Bag buy"},"title":"Buy of Bag the Module \"Mi carrito\"","tags":[{"name":"Bag buy","type":"feature","displayName":"Bag buy"}],"startTime":"2023-09-14T16:31:45.147-05:00[America/Bogota]","duration":69763,"testFailureCause":{"errorType":"org.openqa.selenium.ElementClickInterceptedException","message":"element click intercepted: Element \u003cinput id\u003d\"ship-to-different-address-checkbox\" class\u003d\"woocommerce-form__input woocommerce-form__input-checkbox input-checkbox\" type\u003d\"checkbox\" name\u003d\"ship_to_different_address\" value\u003d\"1\"\u003e is not clickable at point (497, 912). Other element would receive the click: \u003cdiv class\u003d\"message_bar\"\u003e...\u003c/div\u003e\n  (Session info: chrome\u003d116.0.5845.188)\nBuild info: version: \u00273.141.59\u0027, revision: \u0027e82be7d358\u0027, time: \u00272018-11-14T08:17:03\u0027\nSystem info: host: \u0027DESKTOP-SN1JVCC\u0027, ip: \u0027192.168.56.1\u0027, os.name: \u0027Windows 10\u0027, os.arch: \u0027amd64\u0027, os.version: \u002710.0\u0027, java.version: \u00271.8.0_161\u0027\nDriver info: org.openqa.selenium.chrome.ChromeDriver\nCapabilities {acceptInsecureCerts: false, browserName: chrome, browserVersion: 116.0.5845.188, chrome: {chromedriverVersion: 116.0.5845.96 (1a3918166880..., userDataDir: C:\\Users\\FABRIC~1\\AppData\\L...}, fedcm:accounts: true, goog:chromeOptions: {debuggerAddress: localhost:59975}, javascriptEnabled: true, networkConnectionEnabled: false, pageLoadStrategy: normal, platform: WINDOWS, platformName: WINDOWS, proxy: Proxy(), setWindowRect: true, strictFileInteractability: false, timeouts: {implicit: 0, pageLoad: 300000, script: 30000}, unhandledPromptBehavior: dismiss and notify, webauthn:extension:credBlob: true, webauthn:extension:largeBlob: true, webauthn:extension:minPinLength: true, webauthn:extension:prf: true, webauthn:virtualAuthenticators: true}\nSession ID: 4903b9d8a307dc9daa7a46383c3f82c2","stackTrace":[{"declaringClass":"com.co.bonbonite.tasks.FacturationBag","methodName":"performAs","fileName":"FacturationBag.java","lineNumber":94},{"declaringClass":"com.co.bonbonite.stepsdefinitions.BagStepsDefinitions","methodName":"theUserSelectAProductInTheWalletsModuleCarritoAndCompleteTheFormsForFacturation","fileName":"BagStepsDefinitions.java","lineNumber":58},{"declaringClass":"cucumber.runner.Runner","methodName":"runPickle","fileName":"Runner.java","lineNumber":80},{"declaringClass":"worker.org.gradle.process.internal.worker.GradleWorkerMain","methodName":"run","fileName":"GradleWorkerMain.java","lineNumber":69},{"declaringClass":"worker.org.gradle.process.internal.worker.GradleWorkerMain","methodName":"main","fileName":"GradleWorkerMain.java","lineNumber":74}]},"testFailureClassname":"org.openqa.selenium.ElementClickInterceptedException","testFailureMessage":"element click intercepted: Element \u003cinput id\u003d\"ship-to-different-address-checkbox\" class\u003d\"woocommerce-form__input woocommerce-form__input-checkbox input-checkbox\" type\u003d\"checkbox\" name\u003d\"ship_to_different_address\" value\u003d\"1\"\u003e is not clickable at point (497, 912). Other element would receive the click: \u003cdiv class\u003d\"message_bar\"\u003e...\u003c/div\u003e\n  (Session info: chrome\u003d116.0.5845.188)\nBuild info: version: \u00273.141.59\u0027, revision: \u0027e82be7d358\u0027, time: \u00272018-11-14T08:17:03\u0027\nSystem info: host: \u0027DESKTOP-SN1JVCC\u0027, ip: \u0027192.168.56.1\u0027, os.name: \u0027Windows 10\u0027, os.arch: \u0027amd64\u0027, os.version: \u002710.0\u0027, java.version: \u00271.8.0_161\u0027\nDriver info: org.openqa.selenium.chrome.ChromeDriver\nCapabilities {acceptInsecureCerts: false, browserName: chrome, browserVersion: 116.0.5845.188, chrome: {chromedriverVersion: 116.0.5845.96 (1a3918166880..., userDataDir: C:\\Users\\FABRIC~1\\AppData\\L...}, fedcm:accounts: true, goog:chromeOptions: {debuggerAddress: localhost:59975}, javascriptEnabled: true, networkConnectionEnabled: false, pageLoadStrategy: normal, platform: WINDOWS, platformName: WINDOWS, proxy: Proxy(), setWindowRect: true, strictFileInteractability: false, timeouts: {implicit: 0, pageLoad: 300000, script: 30000}, unhandledPromptBehavior: dismiss and notify, webauthn:extension:credBlob: true, webauthn:extension:largeBlob: true, webauthn:extension:minPinLength: true, webauthn:extension:prf: true, webauthn:virtualAuthenticators: true}\nSession ID: 4903b9d8a307dc9daa7a46383c3f82c2","testFailureSummary":"ERROR;org.openqa.selenium.ElementClickInterceptedException;element click intercepted: Element \u003cinput id\u003d\"ship-to-different-address-checkbox\" class\u003d\"woocommerce-form__input woocommerce-form__input-checkbox input-checkbox\" type\u003d\"checkbox\" name\u003d\"ship_to_different_address\" value\u003d\"1\"\u003e is not clickable at point (497, 912). Other element would receive the click: \u003cdiv class\u003d\"message_bar\"\u003e...\u003c/div\u003e\n  (Session info: chrome\u003d116.0.5845.188)\nBuild info: version: \u00273.141.59\u0027, revision: \u0027e82be7d358\u0027, time: \u00272018-11-14T08:17:03\u0027\nSystem info: host: \u0027DESKTOP-SN1JVCC\u0027, ip: \u0027192.168.56.1\u0027, os.name: \u0027Windows 10\u0027, os.arch: \u0027amd64\u0027, os.version: \u002710.0\u0027, java.version: \u00271.8.0_161\u0027\nDriver info: org.openqa.selenium.chrome.ChromeDriver\nCapabilities {acceptInsecureCerts: false, browserName: chrome, browserVersion: 116.0.5845.188, chrome: {chromedriverVersion: 116.0.5845.96 (1a3918166880..., userDataDir: C:\\Users\\FABRIC~1\\AppData\\L...}, fedcm:accounts: true, goog:chromeOptions: {debuggerAddress: localhost:59975}, javascriptEnabled: true, networkConnectionEnabled: false, pageLoadStrategy: normal, platform: WINDOWS, platformName: WINDOWS, proxy: Proxy(), setWindowRect: true, strictFileInteractability: false, timeouts: {implicit: 0, pageLoad: 300000, script: 30000}, unhandledPromptBehavior: dismiss and notify, webauthn:extension:credBlob: true, webauthn:extension:largeBlob: true, webauthn:extension:minPinLength: true, webauthn:extension:prf: true, webauthn:virtualAuthenticators: true}\nSession ID: 4903b9d8a307dc9daa7a46383c3f82c2;FacturationBag.java","projectKey":"","annotatedResult":"ERROR","sessionId":"4903b9d8a307dc9daa7a46383c3f82c2","driver":"chrome","isManualTestingUpToDate":false,"manual":false,"testSource":"Cucumber","actors":[{"name":"Rosa","can":["browse the web"]}],"result":"ERROR"}