{"name":"Aggregate of Bag Successfull the \"Mi carrito\"","id":"bag-buy;aggregate-of-bag-successfull-the-\"mi-carrito\"","testSteps":[{"number":1,"description":"Given he user enter the website","duration":3939,"startTime":"2023-09-14T16:33:15.412-05:00[America/Bogota]","result":"SUCCESS","precondition":false,"level":0,"children":[{"number":2,"description":"Rosa opens the https://www.bon-bonite.com/","duration":3917,"startTime":"2023-09-14T16:33:15.416-05:00[America/Bogota]","result":"SUCCESS","precondition":false,"level":1}]},{"number":3,"description":"When The user select a product in the Wallets module","duration":121,"startTime":"2023-09-14T16:33:19.352-05:00[America/Bogota]","exception":{"errorType":"org.openqa.selenium.NoSuchWindowException","message":"no such window: target window already closed\nfrom unknown error: web view not found\n  (Session info: chrome\u003d116.0.5845.188)\nBuild info: version: \u00273.141.59\u0027, revision: \u0027e82be7d358\u0027, time: \u00272018-11-14T08:17:03\u0027\nSystem info: host: \u0027DESKTOP-SN1JVCC\u0027, ip: \u0027192.168.56.1\u0027, os.name: \u0027Windows 10\u0027, os.arch: \u0027amd64\u0027, os.version: \u002710.0\u0027, java.version: \u00271.8.0_161\u0027\nDriver info: org.openqa.selenium.chrome.ChromeDriver\nCapabilities {acceptInsecureCerts: false, browserName: chrome, browserVersion: 116.0.5845.188, chrome: {chromedriverVersion: 116.0.5845.96 (1a3918166880..., userDataDir: C:\\Users\\FABRIC~1\\AppData\\L...}, fedcm:accounts: true, goog:chromeOptions: {debuggerAddress: localhost:60059}, javascriptEnabled: true, networkConnectionEnabled: false, pageLoadStrategy: normal, platform: WINDOWS, platformName: WINDOWS, proxy: Proxy(), setWindowRect: true, strictFileInteractability: false, timeouts: {implicit: 0, pageLoad: 300000, script: 30000}, unhandledPromptBehavior: dismiss and notify, webauthn:extension:credBlob: true, webauthn:extension:largeBlob: true, webauthn:extension:minPinLength: true, webauthn:extension:prf: true, webauthn:virtualAuthenticators: true}\nSession ID: fe9e8b6a2bb125ae50ec3883f5b87075\n*** Element info: {Using\u003dxpath, value\u003d(//a[@href\u003d\u0027https://www.bon-bonite.com/categoria-producto/bolsos-mujer/\u0027])[1]}","stackTrace":[{"declaringClass":"com.co.bonbonite.tasks.BagsBuy","methodName":"performAs","fileName":"BagsBuy.java","lineNumber":12},{"declaringClass":"com.co.bonbonite.stepsdefinitions.BagStepsDefinitions","methodName":"TheUserSelectAProductInTheWalletsModule","fileName":"BagStepsDefinitions.java","lineNumber":21},{"declaringClass":"cucumber.runner.Runner","methodName":"runPickle","fileName":"Runner.java","lineNumber":80},{"declaringClass":"worker.org.gradle.process.internal.worker.GradleWorkerMain","methodName":"run","fileName":"GradleWorkerMain.java","lineNumber":69},{"declaringClass":"worker.org.gradle.process.internal.worker.GradleWorkerMain","methodName":"main","fileName":"GradleWorkerMain.java","lineNumber":74}]},"result":"ERROR","precondition":false,"level":0,"children":[{"number":4,"description":"Rosa bags buy","duration":99,"startTime":"2023-09-14T16:33:19.367-05:00[America/Bogota]","exception":{"errorType":"org.openqa.selenium.NoSuchWindowException","message":"no such window: target window already closed\nfrom unknown error: web view not found\n  (Session info: chrome\u003d116.0.5845.188)\nBuild info: version: \u00273.141.59\u0027, revision: \u0027e82be7d358\u0027, time: \u00272018-11-14T08:17:03\u0027\nSystem info: host: \u0027DESKTOP-SN1JVCC\u0027, ip: \u0027192.168.56.1\u0027, os.name: \u0027Windows 10\u0027, os.arch: \u0027amd64\u0027, os.version: \u002710.0\u0027, java.version: \u00271.8.0_161\u0027\nDriver info: org.openqa.selenium.chrome.ChromeDriver\nCapabilities {acceptInsecureCerts: false, browserName: chrome, browserVersion: 116.0.5845.188, chrome: {chromedriverVersion: 116.0.5845.96 (1a3918166880..., userDataDir: C:\\Users\\FABRIC~1\\AppData\\L...}, fedcm:accounts: true, goog:chromeOptions: {debuggerAddress: localhost:60059}, javascriptEnabled: true, networkConnectionEnabled: false, pageLoadStrategy: normal, platform: WINDOWS, platformName: WINDOWS, proxy: Proxy(), setWindowRect: true, strictFileInteractability: false, timeouts: {implicit: 0, pageLoad: 300000, script: 30000}, unhandledPromptBehavior: dismiss and notify, webauthn:extension:credBlob: true, webauthn:extension:largeBlob: true, webauthn:extension:minPinLength: true, webauthn:extension:prf: true, webauthn:virtualAuthenticators: true}\nSession ID: fe9e8b6a2bb125ae50ec3883f5b87075\n*** Element info: {Using\u003dxpath, value\u003d(//a[@href\u003d\u0027https://www.bon-bonite.com/categoria-producto/bolsos-mujer/\u0027])[1]}","stackTrace":[{"declaringClass":"com.co.bonbonite.tasks.BagsBuy","methodName":"performAs","fileName":"BagsBuy.java","lineNumber":12},{"declaringClass":"com.co.bonbonite.stepsdefinitions.BagStepsDefinitions","methodName":"TheUserSelectAProductInTheWalletsModule","fileName":"BagStepsDefinitions.java","lineNumber":21},{"declaringClass":"cucumber.runner.Runner","methodName":"runPickle","fileName":"Runner.java","lineNumber":80},{"declaringClass":"worker.org.gradle.process.internal.worker.GradleWorkerMain","methodName":"run","fileName":"GradleWorkerMain.java","lineNumber":69},{"declaringClass":"worker.org.gradle.process.internal.worker.GradleWorkerMain","methodName":"main","fileName":"GradleWorkerMain.java","lineNumber":74}]},"result":"ERROR","precondition":false,"level":1,"children":[{"number":5,"description":"Rosa clicks on ir al modulo de bolsos","duration":80,"startTime":"2023-09-14T16:33:19.377-05:00[America/Bogota]","exception":{"errorType":"org.openqa.selenium.NoSuchWindowException","message":"no such window: target window already closed\nfrom unknown error: web view not found\n  (Session info: chrome\u003d116.0.5845.188)\nBuild info: version: \u00273.141.59\u0027, revision: \u0027e82be7d358\u0027, time: \u00272018-11-14T08:17:03\u0027\nSystem info: host: \u0027DESKTOP-SN1JVCC\u0027, ip: \u0027192.168.56.1\u0027, os.name: \u0027Windows 10\u0027, os.arch: \u0027amd64\u0027, os.version: \u002710.0\u0027, java.version: \u00271.8.0_161\u0027\nDriver info: org.openqa.selenium.chrome.ChromeDriver\nCapabilities {acceptInsecureCerts: false, browserName: chrome, browserVersion: 116.0.5845.188, chrome: {chromedriverVersion: 116.0.5845.96 (1a3918166880..., userDataDir: C:\\Users\\FABRIC~1\\AppData\\L...}, fedcm:accounts: true, goog:chromeOptions: {debuggerAddress: localhost:60059}, javascriptEnabled: true, networkConnectionEnabled: false, pageLoadStrategy: normal, platform: WINDOWS, platformName: WINDOWS, proxy: Proxy(), setWindowRect: true, strictFileInteractability: false, timeouts: {implicit: 0, pageLoad: 300000, script: 30000}, unhandledPromptBehavior: dismiss and notify, webauthn:extension:credBlob: true, webauthn:extension:largeBlob: true, webauthn:extension:minPinLength: true, webauthn:extension:prf: true, webauthn:virtualAuthenticators: true}\nSession ID: fe9e8b6a2bb125ae50ec3883f5b87075\n*** Element info: {Using\u003dxpath, value\u003d(//a[@href\u003d\u0027https://www.bon-bonite.com/categoria-producto/bolsos-mujer/\u0027])[1]}","stackTrace":[{"declaringClass":"com.co.bonbonite.tasks.BagsBuy","methodName":"performAs","fileName":"BagsBuy.java","lineNumber":12},{"declaringClass":"com.co.bonbonite.stepsdefinitions.BagStepsDefinitions","methodName":"TheUserSelectAProductInTheWalletsModule","fileName":"BagStepsDefinitions.java","lineNumber":21},{"declaringClass":"cucumber.runner.Runner","methodName":"runPickle","fileName":"Runner.java","lineNumber":80},{"declaringClass":"worker.org.gradle.process.internal.worker.GradleWorkerMain","methodName":"run","fileName":"GradleWorkerMain.java","lineNumber":69},{"declaringClass":"worker.org.gradle.process.internal.worker.GradleWorkerMain","methodName":"main","fileName":"GradleWorkerMain.java","lineNumber":74}]},"result":"ERROR","precondition":false,"level":2}]}]},{"number":6,"description":"Then the user will buy a Bag","duration":10,"startTime":"2023-09-14T16:33:19.490-05:00[America/Bogota]","result":"SKIPPED","precondition":false,"level":0}],"userStory":{"id":"bag-buy","storyName":"Bag buy","path":"src/test/resources/features/bag.feature","narrative":"  i need buy a bag","type":"feature"},"featureTag":{"name":"Features/Bag buy","type":"feature","displayName":"Features/Bag buy"},"title":"Aggregate of Bag Successfull the \"Mi carrito\"","tags":[{"name":"Bag buy","type":"feature","displayName":"Bag buy"}],"startTime":"2023-09-14T16:33:15.396-05:00[America/Bogota]","duration":4105,"testFailureCause":{"errorType":"org.openqa.selenium.NoSuchWindowException","message":"no such window: target window already closed\nfrom unknown error: web view not found\n  (Session info: chrome\u003d116.0.5845.188)\nBuild info: version: \u00273.141.59\u0027, revision: \u0027e82be7d358\u0027, time: \u00272018-11-14T08:17:03\u0027\nSystem info: host: \u0027DESKTOP-SN1JVCC\u0027, ip: \u0027192.168.56.1\u0027, os.name: \u0027Windows 10\u0027, os.arch: \u0027amd64\u0027, os.version: \u002710.0\u0027, java.version: \u00271.8.0_161\u0027\nDriver info: org.openqa.selenium.chrome.ChromeDriver\nCapabilities {acceptInsecureCerts: false, browserName: chrome, browserVersion: 116.0.5845.188, chrome: {chromedriverVersion: 116.0.5845.96 (1a3918166880..., userDataDir: C:\\Users\\FABRIC~1\\AppData\\L...}, fedcm:accounts: true, goog:chromeOptions: {debuggerAddress: localhost:60059}, javascriptEnabled: true, networkConnectionEnabled: false, pageLoadStrategy: normal, platform: WINDOWS, platformName: WINDOWS, proxy: Proxy(), setWindowRect: true, strictFileInteractability: false, timeouts: {implicit: 0, pageLoad: 300000, script: 30000}, unhandledPromptBehavior: dismiss and notify, webauthn:extension:credBlob: true, webauthn:extension:largeBlob: true, webauthn:extension:minPinLength: true, webauthn:extension:prf: true, webauthn:virtualAuthenticators: true}\nSession ID: fe9e8b6a2bb125ae50ec3883f5b87075\n*** Element info: {Using\u003dxpath, value\u003d(//a[@href\u003d\u0027https://www.bon-bonite.com/categoria-producto/bolsos-mujer/\u0027])[1]}","stackTrace":[{"declaringClass":"com.co.bonbonite.tasks.BagsBuy","methodName":"performAs","fileName":"BagsBuy.java","lineNumber":12},{"declaringClass":"com.co.bonbonite.stepsdefinitions.BagStepsDefinitions","methodName":"TheUserSelectAProductInTheWalletsModule","fileName":"BagStepsDefinitions.java","lineNumber":21},{"declaringClass":"cucumber.runner.Runner","methodName":"runPickle","fileName":"Runner.java","lineNumber":80},{"declaringClass":"worker.org.gradle.process.internal.worker.GradleWorkerMain","methodName":"run","fileName":"GradleWorkerMain.java","lineNumber":69},{"declaringClass":"worker.org.gradle.process.internal.worker.GradleWorkerMain","methodName":"main","fileName":"GradleWorkerMain.java","lineNumber":74}]},"testFailureClassname":"org.openqa.selenium.NoSuchWindowException","testFailureMessage":"no such window: target window already closed\nfrom unknown error: web view not found\n  (Session info: chrome\u003d116.0.5845.188)\nBuild info: version: \u00273.141.59\u0027, revision: \u0027e82be7d358\u0027, time: \u00272018-11-14T08:17:03\u0027\nSystem info: host: \u0027DESKTOP-SN1JVCC\u0027, ip: \u0027192.168.56.1\u0027, os.name: \u0027Windows 10\u0027, os.arch: \u0027amd64\u0027, os.version: \u002710.0\u0027, java.version: \u00271.8.0_161\u0027\nDriver info: org.openqa.selenium.chrome.ChromeDriver\nCapabilities {acceptInsecureCerts: false, browserName: chrome, browserVersion: 116.0.5845.188, chrome: {chromedriverVersion: 116.0.5845.96 (1a3918166880..., userDataDir: C:\\Users\\FABRIC~1\\AppData\\L...}, fedcm:accounts: true, goog:chromeOptions: {debuggerAddress: localhost:60059}, javascriptEnabled: true, networkConnectionEnabled: false, pageLoadStrategy: normal, platform: WINDOWS, platformName: WINDOWS, proxy: Proxy(), setWindowRect: true, strictFileInteractability: false, timeouts: {implicit: 0, pageLoad: 300000, script: 30000}, unhandledPromptBehavior: dismiss and notify, webauthn:extension:credBlob: true, webauthn:extension:largeBlob: true, webauthn:extension:minPinLength: true, webauthn:extension:prf: true, webauthn:virtualAuthenticators: true}\nSession ID: fe9e8b6a2bb125ae50ec3883f5b87075\n*** Element info: {Using\u003dxpath, value\u003d(//a[@href\u003d\u0027https://www.bon-bonite.com/categoria-producto/bolsos-mujer/\u0027])[1]}","testFailureSummary":"ERROR;org.openqa.selenium.NoSuchWindowException;no such window: target window already closed\nfrom unknown error: web view not found\n  (Session info: chrome\u003d116.0.5845.188)\nBuild info: version: \u00273.141.59\u0027, revision: \u0027e82be7d358\u0027, time: \u00272018-11-14T08:17:03\u0027\nSystem info: host: \u0027DESKTOP-SN1JVCC\u0027, ip: \u0027192.168.56.1\u0027, os.name: \u0027Windows 10\u0027, os.arch: \u0027amd64\u0027, os.version: \u002710.0\u0027, java.version: \u00271.8.0_161\u0027\nDriver info: org.openqa.selenium.chrome.ChromeDriver\nCapabilities {acceptInsecureCerts: false, browserName: chrome, browserVersion: 116.0.5845.188, chrome: {chromedriverVersion: 116.0.5845.96 (1a3918166880..., userDataDir: C:\\Users\\FABRIC~1\\AppData\\L...}, fedcm:accounts: true, goog:chromeOptions: {debuggerAddress: localhost:60059}, javascriptEnabled: true, networkConnectionEnabled: false, pageLoadStrategy: normal, platform: WINDOWS, platformName: WINDOWS, proxy: Proxy(), setWindowRect: true, strictFileInteractability: false, timeouts: {implicit: 0, pageLoad: 300000, script: 30000}, unhandledPromptBehavior: dismiss and notify, webauthn:extension:credBlob: true, webauthn:extension:largeBlob: true, webauthn:extension:minPinLength: true, webauthn:extension:prf: true, webauthn:virtualAuthenticators: true}\nSession ID: fe9e8b6a2bb125ae50ec3883f5b87075\n*** Element info: {Using\u003dxpath, value\u003d(//a[@href\u003d\u0027https://www.bon-bonite.com/categoria-producto/bolsos-mujer/\u0027])[1]};BagsBuy.java","projectKey":"","annotatedResult":"ERROR","sessionId":"fe9e8b6a2bb125ae50ec3883f5b87075","driver":"chrome","isManualTestingUpToDate":false,"manual":false,"testSource":"Cucumber","actors":[{"name":"Rosa","can":["browse the web"]}],"result":"ERROR"}